Metadata-Version: 2.1
Name: type-strict
Version: 0.1.0
Summary: Python's missing runtime type checker
Home-page: https://github.com/Alex0Blackwell/type-strict
Author: Alex Blackwell
Author-email: alex.blackwell314@gmail.com
License: MIT
Platform: UNKNOWN
Classifier: Programming Language :: Python :: 3
Classifier: License :: OSI Approved :: MIT License
Classifier: Operating System :: OS Independent
Requires-Python: >=3.9
License-File: LICENSE
